README.txt
setup.py
JoeLogTools.egg-info/PKG-INFO
JoeLogTools.egg-info/SOURCES.txt
JoeLogTools.egg-info/dependency_links.txt
JoeLogTools.egg-info/top_level.txt
joelogtools/__init__.py
joelogtools/joseph_logging_tools.py