Metadata-Version: 1.0
Name: JoeLogTools
Version: 0.4.0
Summary: UNKNOWN
Home-page: https://bitbucket.org/jmg099120/joelogtools
Author: Joseph Gordon
Author-email: j.gordon.matthew@gmail.com
License: LICENSE.txt
Platform: UNKNOWN
